README
setup.py
nodist/__init__.py
nodist/__main__.py
nodist/cli.py
nodist/installer.py
nodist/misc.py
nodist.egg-info/PKG-INFO
nodist.egg-info/SOURCES.txt
nodist.egg-info/dependency_links.txt
nodist.egg-info/top_level.txt
scripts/nodist