Metadata-Version: 1.1
Name: nodist
Version: 0.3.1
Summary: Node.js version manager
Home-page: https://github.com/keremc/nodist
Author: Kerem Çakırer
Author-email: kcakirer@hotmail.com
License: GNU General Public License, version 2
Platform: UNKNOWN
Classifier: Development Status :: 7 - Inactive
Classifier: Intended Audience :: Developers
Classifier: License :: OSI Approved :: GNU General Public License v2 (GPLv2)
Classifier: Operating System :: POSIX :: Linux
Classifier: Programming Language :: Python :: 2
Classifier: Programming Language :: Python :: 2.6
Classifier: Programming Language :: Python :: 2.7
Classifier: Programming Language :: Python :: Implementation :: CPython
Classifier: Topic :: Software Development
Classifier: Topic :: Utilities
